{
	"inputs" : 
	[
		{
			"path" : "CMakeLists.txt"
		},
		{
			"isGenerated" : true,
			"path" : "build/Release/bin/CMakeFiles/3.22.1/CMakeSystem.cmake"
		},
		{
			"isCMake" : true,
			"isExternal" : true,
			"path" : "/usr/share/cmake-3.22/Modules/CMakeSystemSpecificInitialize.cmake"
		},
		{
			"isGenerated" : true,
			"path" : "build/Release/bin/CMakeFiles/3.22.1/CMakeCCompiler.cmake"
		},
		{
			"isGenerated" : true,
			"path" : "build/Release/bin/CMakeFiles/3.22.1/CMakeCXXCompiler.cmake"
		},
		{
			"isCMake" : true,
			"isExternal" : true,
			"path" : "/usr/share/cmake-3.22/Modules/CMakeSystemSpecificInformation.cmake"
		},
		{
			"isCMake" : true,
			"isExternal" : true,
			"path" : "/usr/share/cmake-3.22/Modules/CMakeGenericSystem.cmake"
		},
		{
			"isCMake" : true,
			"isExternal" : true,
			"path" : "/usr/share/cmake-3.22/Modules/CMakeInitializeConfigs.cmake"
		},
		{
			"isCMake" : true,
			"isExternal" : true,
			"path" : "/usr/share/cmake-3.22/Modules/Platform/Linux.cmake"
		},
		{
			"isCMake" : true,
			"isExternal" : true,
			"path" : "/usr/share/cmake-3.22/Modules/Platform/UnixPaths.cmake"
		},
		{
			"isCMake" : true,
			"isExternal" : true,
			"path" : "/usr/share/cmake-3.22/Modules/CMakeCInformation.cmake"
		},
		{
			"isCMake" : true,
			"isExternal" : true,
			"path" : "/usr/share/cmake-3.22/Modules/CMakeLanguageInformation.cmake"
		},
		{
			"isCMake" : true,
			"isExternal" : true,
			"path" : "/usr/share/cmake-3.22/Modules/Compiler/Clang-C.cmake"
		},
		{
			"isCMake" : true,
			"isExternal" : true,
			"path" : "/usr/share/cmake-3.22/Modules/Compiler/Clang.cmake"
		},
		{
			"isCMake" : true,
			"isExternal" : true,
			"path" : "/usr/share/cmake-3.22/Modules/Compiler/CMakeCommonCompilerMacros.cmake"
		},
		{
			"isCMake" : true,
			"isExternal" : true,
			"path" : "/usr/share/cmake-3.22/Modules/Compiler/GNU.cmake"
		},
		{
			"isCMake" : true,
			"isExternal" : true,
			"path" : "/usr/share/cmake-3.22/Modules/Compiler/CMakeCommonCompilerMacros.cmake"
		},
		{
			"isCMake" : true,
			"isExternal" : true,
			"path" : "/usr/share/cmake-3.22/Modules/Platform/Linux-Clang-C.cmake"
		},
		{
			"isCMake" : true,
			"isExternal" : true,
			"path" : "/usr/share/cmake-3.22/Modules/Platform/Linux-GNU-C.cmake"
		},
		{
			"isCMake" : true,
			"isExternal" : true,
			"path" : "/usr/share/cmake-3.22/Modules/Platform/Linux-GNU.cmake"
		},
		{
			"isCMake" : true,
			"isExternal" : true,
			"path" : "/usr/share/cmake-3.22/Modules/CMakeCommonLanguageInclude.cmake"
		},
		{
			"isCMake" : true,
			"isExternal" : true,
			"path" : "/usr/share/cmake-3.22/Modules/CMakeCXXInformation.cmake"
		},
		{
			"isCMake" : true,
			"isExternal" : true,
			"path" : "/usr/share/cmake-3.22/Modules/CMakeLanguageInformation.cmake"
		},
		{
			"isCMake" : true,
			"isExternal" : true,
			"path" : "/usr/share/cmake-3.22/Modules/Compiler/Clang-CXX.cmake"
		},
		{
			"isCMake" : true,
			"isExternal" : true,
			"path" : "/usr/share/cmake-3.22/Modules/Compiler/Clang.cmake"
		},
		{
			"isCMake" : true,
			"isExternal" : true,
			"path" : "/usr/share/cmake-3.22/Modules/Platform/Linux-Clang-CXX.cmake"
		},
		{
			"isCMake" : true,
			"isExternal" : true,
			"path" : "/usr/share/cmake-3.22/Modules/Platform/Linux-GNU-CXX.cmake"
		},
		{
			"isCMake" : true,
			"isExternal" : true,
			"path" : "/usr/share/cmake-3.22/Modules/Platform/Linux-GNU.cmake"
		},
		{
			"isCMake" : true,
			"isExternal" : true,
			"path" : "/usr/share/cmake-3.22/Modules/CMakeCommonLanguageInclude.cmake"
		},
		{
			"isCMake" : true,
			"isExternal" : true,
			"path" : "/usr/share/cmake-3.22/Modules/CTest.cmake"
		},
		{
			"isCMake" : true,
			"isExternal" : true,
			"path" : "/usr/share/cmake-3.22/Modules/CTestUseLaunchers.cmake"
		},
		{
			"isCMake" : true,
			"isExternal" : true,
			"path" : "/usr/share/cmake-3.22/Modules/CTestTargets.cmake"
		},
		{
			"isCMake" : true,
			"isExternal" : true,
			"path" : "/usr/share/cmake-3.22/Modules/DartConfiguration.tcl.in"
		},
		{
			"isGenerated" : true,
			"path" : "build/Release/bin/compile_commands.json"
		},
		{
			"path" : "third-party/cmake/modules/SDLOptions.cmake"
		},
		{
			"isCMake" : true,
			"isExternal" : true,
			"path" : "/usr/share/cmake-3.22/Modules/GoogleTest.cmake"
		},
		{
			"path" : "test/CMakeLists.txt"
		},
		{
			"path" : "test/goalc/CMakeLists.txt"
		},
		{
			"path" : "test/offline/CMakeLists.txt"
		},
		{
			"path" : "third-party/curl/CMakeLists.txt"
		},
		{
			"path" : "third-party/curl/CMake/Utilities.cmake"
		},
		{
			"path" : "third-party/curl/CMake/Macros.cmake"
		},
		{
			"isCMake" : true,
			"isExternal" : true,
			"path" : "/usr/share/cmake-3.22/Modules/CMakeDependentOption.cmake"
		},
		{
			"isCMake" : true,
			"isExternal" : true,
			"path" : "/usr/share/cmake-3.22/Modules/CheckCCompilerFlag.cmake"
		},
		{
			"isCMake" : true,
			"isExternal" : true,
			"path" : "/usr/share/cmake-3.22/Modules/CheckCSourceCompiles.cmake"
		},
		{
			"isCMake" : true,
			"isExternal" : true,
			"path" : "/usr/share/cmake-3.22/Modules/Internal/CheckSourceCompiles.cmake"
		},
		{
			"isCMake" : true,
			"isExternal" : true,
			"path" : "/usr/share/cmake-3.22/Modules/Internal/CheckCompilerFlag.cmake"
		},
		{
			"isCMake" : true,
			"isExternal" : true,
			"path" : "/usr/share/cmake-3.22/Modules/Internal/CheckSourceCompiles.cmake"
		},
		{
			"isCMake" : true,
			"isExternal" : true,
			"path" : "/usr/share/cmake-3.22/Modules/CMakeCheckCompilerFlagCommonPatterns.cmake"
		},
		{
			"path" : "third-party/curl/CMake/PickyWarnings.cmake"
		},
		{
			"isCMake" : true,
			"isExternal" : true,
			"path" : "/usr/share/cmake-3.22/Modules/CheckCCompilerFlag.cmake"
		},
		{
			"path" : "third-party/curl/CMake/CurlSymbolHiding.cmake"
		},
		{
			"isCMake" : true,
			"isExternal" : true,
			"path" : "/usr/share/cmake-3.22/Modules/CheckCSourceCompiles.cmake"
		},
		{
			"isCMake" : true,
			"isExternal" : true,
			"path" : "/usr/share/cmake-3.22/Modules/CheckStructHasMember.cmake"
		},
		{
			"isCMake" : true,
			"isExternal" : true,
			"path" : "/usr/share/cmake-3.22/Modules/CheckCSourceCompiles.cmake"
		},
		{
			"isCMake" : true,
			"isExternal" : true,
			"path" : "/usr/share/cmake-3.22/Modules/CheckCXXSourceCompiles.cmake"
		},
		{
			"isCMake" : true,
			"isExternal" : true,
			"path" : "/usr/share/cmake-3.22/Modules/Internal/CheckSourceCompiles.cmake"
		},
		{
			"isCMake" : true,
			"isExternal" : true,
			"path" : "/usr/share/cmake-3.22/Modules/FindPerl.cmake"
		},
		{
			"isCMake" : true,
			"isExternal" : true,
			"path" : "/usr/share/cmake-3.22/Modules/FindCygwin.cmake"
		},
		{
			"isCMake" : true,
			"isExternal" : true,
			"path" : "/usr/share/cmake-3.22/Modules/FindMsys.cmake"
		},
		{
			"isCMake" : true,
			"isExternal" : true,
			"path" : "/usr/share/cmake-3.22/Modules/FindPackageHandleStandardArgs.cmake"
		},
		{
			"isCMake" : true,
			"isExternal" : true,
			"path" : "/usr/share/cmake-3.22/Modules/FindPackageMessage.cmake"
		},
		{
			"isCMake" : true,
			"isExternal" : true,
			"path" : "/usr/share/cmake-3.22/Modules/CMakePushCheckState.cmake"
		},
		{
			"isCMake" : true,
			"isExternal" : true,
			"path" : "/usr/share/cmake-3.22/Modules/CheckFunctionExists.cmake"
		},
		{
			"isCMake" : true,
			"isExternal" : true,
			"path" : "/usr/share/cmake-3.22/Modules/CheckIncludeFile.cmake"
		},
		{
			"isCMake" : true,
			"isExternal" : true,
			"path" : "/usr/share/cmake-3.22/Modules/CheckIncludeFiles.cmake"
		},
		{
			"isCMake" : true,
			"isExternal" : true,
			"path" : "/usr/share/cmake-3.22/Modules/CheckLibraryExists.cmake"
		},
		{
			"isCMake" : true,
			"isExternal" : true,
			"path" : "/usr/share/cmake-3.22/Modules/CheckSymbolExists.cmake"
		},
		{
			"isCMake" : true,
			"isExternal" : true,
			"path" : "/usr/share/cmake-3.22/Modules/CheckTypeSize.cmake"
		},
		{
			"isCMake" : true,
			"isExternal" : true,
			"path" : "/usr/share/cmake-3.22/Modules/CheckIncludeFile.cmake"
		},
		{
			"isCMake" : true,
			"isExternal" : true,
			"path" : "/usr/share/cmake-3.22/Modules/CheckIncludeFileCXX.cmake"
		},
		{
			"isCMake" : true,
			"isExternal" : true,
			"path" : "/usr/share/cmake-3.22/Modules/CheckCSourceCompiles.cmake"
		},
		{
			"isCMake" : true,
			"isExternal" : true,
			"path" : "/usr/share/cmake-3.22/Modules/FindThreads.cmake"
		},
		{
			"isCMake" : true,
			"isExternal" : true,
			"path" : "/usr/share/cmake-3.22/Modules/CheckLibraryExists.cmake"
		},
		{
			"isCMake" : true,
			"isExternal" : true,
			"path" : "/usr/share/cmake-3.22/Modules/CheckIncludeFile.cmake"
		},
		{
			"isCMake" : true,
			"isExternal" : true,
			"path" : "/usr/share/cmake-3.22/Modules/CheckCSourceCompiles.cmake"
		},
		{
			"isCMake" : true,
			"isExternal" : true,
			"path" : "/usr/share/cmake-3.22/Modules/FindPackageHandleStandardArgs.cmake"
		},
		{
			"isCMake" : true,
			"isExternal" : true,
			"path" : "/usr/share/cmake-3.22/Modules/FindPackageMessage.cmake"
		},
		{
			"path" : "third-party/curl/CMake/FindLibPSL.cmake"
		},
		{
			"isCMake" : true,
			"isExternal" : true,
			"path" : "/usr/share/cmake-3.22/Modules/FindPackageHandleStandardArgs.cmake"
		},
		{
			"isCMake" : true,
			"isExternal" : true,
			"path" : "/usr/share/cmake-3.22/Modules/FindPackageMessage.cmake"
		},
		{
			"isCMake" : true,
			"isExternal" : true,
			"path" : "/usr/share/cmake-3.22/Modules/CheckStructHasMember.cmake"
		},
		{
			"path" : "third-party/curl/CMake/OtherTests.cmake"
		},
		{
			"isCMake" : true,
			"isExternal" : true,
			"path" : "/usr/share/cmake-3.22/Modules/CheckCSourceCompiles.cmake"
		},
		{
			"isCMake" : true,
			"isExternal" : true,
			"path" : "/usr/share/cmake-3.22/Modules/CheckCSourceRuns.cmake"
		},
		{
			"isCMake" : true,
			"isExternal" : true,
			"path" : "/usr/share/cmake-3.22/Modules/Internal/CheckSourceRuns.cmake"
		},
		{
			"isCMake" : true,
			"isExternal" : true,
			"path" : "/usr/share/cmake-3.22/Modules/GNUInstallDirs.cmake"
		},
		{
			"path" : "third-party/curl/curl-config.in"
		},
		{
			"path" : "third-party/curl/libcurl.pc.in"
		},
		{
			"isCMake" : true,
			"isExternal" : true,
			"path" : "/usr/share/cmake-3.22/Modules/CMakePackageConfigHelpers.cmake"
		},
		{
			"isCMake" : true,
			"isExternal" : true,
			"path" : "/usr/share/cmake-3.22/Modules/WriteBasicConfigVersionFile.cmake"
		},
		{
			"isCMake" : true,
			"isExternal" : true,
			"path" : "/usr/share/cmake-3.22/Modules/BasicConfigVersion-SameMajorVersion.cmake.in"
		},
		{
			"path" : "third-party/curl/CMake/curl-config.cmake.in"
		},
		{
			"path" : "third-party/curl/CMake/cmake_uninstall.cmake.in"
		},
		{
			"path" : "third-party/curl/lib/CMakeLists.txt"
		},
		{
			"path" : "third-party/curl/lib/curl_config.h.cmake"
		},
		{
			"isGenerated" : true,
			"path" : "build/Release/bin/third-party/curl/lib/Makefile.inc.cmake"
		},
		{
			"isGenerated" : true,
			"path" : "build/Release/bin/third-party/curl/lib/Makefile.soname.cmake"
		},
		{
			"isCMake" : true,
			"isExternal" : true,
			"path" : "/usr/share/cmake-3.22/Modules/CheckCSourceRuns.cmake"
		},
		{
			"path" : "third-party/curl/lib/Makefile.inc"
		},
		{
			"path" : "third-party/curl/lib/Makefile.soname"
		},
		{
			"path" : "third-party/curl/src/CMakeLists.txt"
		},
		{
			"isGenerated" : true,
			"path" : "build/Release/bin/third-party/curl/src/Makefile.inc.cmake"
		},
		{
			"path" : "third-party/curl/src/Makefile.inc"
		},
		{
			"path" : "third-party/curl/tests/CMakeLists.txt"
		},
		{
			"path" : "third-party/curl/tests/data/CMakeLists.txt"
		},
		{
			"isGenerated" : true,
			"path" : "build/Release/bin/third-party/curl/tests/data/Makefile.inc.cmake"
		},
		{
			"path" : "third-party/curl/tests/data/Makefile.inc"
		},
		{
			"path" : "third-party/curl/tests/libtest/CMakeLists.txt"
		},
		{
			"isGenerated" : true,
			"path" : "build/Release/bin/third-party/curl/tests/libtest/Makefile.inc.cmake"
		},
		{
			"path" : "third-party/curl/tests/libtest/Makefile.inc"
		},
		{
			"path" : "third-party/curl/tests/server/CMakeLists.txt"
		},
		{
			"isGenerated" : true,
			"path" : "build/Release/bin/third-party/curl/tests/server/Makefile.inc.cmake"
		},
		{
			"path" : "third-party/curl/tests/server/Makefile.inc"
		},
		{
			"path" : "third-party/curl/tests/unit/CMakeLists.txt"
		},
		{
			"isGenerated" : true,
			"path" : "build/Release/bin/third-party/curl/tests/unit/Makefile.inc.cmake"
		},
		{
			"path" : "third-party/curl/tests/unit/Makefile.inc"
		},
		{
			"path" : "third-party/replxx/CMakeLists.txt"
		},
		{
			"isCMake" : true,
			"isExternal" : true,
			"path" : "/usr/share/cmake-3.22/Modules/CMakePackageConfigHelpers.cmake"
		},
		{
			"isCMake" : true,
			"isExternal" : true,
			"path" : "/usr/share/cmake-3.22/Modules/WriteBasicConfigVersionFile.cmake"
		},
		{
			"isCMake" : true,
			"isExternal" : true,
			"path" : "/usr/share/cmake-3.22/Modules/CMakeDependentOption.cmake"
		},
		{
			"isCMake" : true,
			"isExternal" : true,
			"path" : "/usr/share/cmake-3.22/Modules/GenerateExportHeader.cmake"
		},
		{
			"isCMake" : true,
			"isExternal" : true,
			"path" : "/usr/share/cmake-3.22/Modules/CheckCCompilerFlag.cmake"
		},
		{
			"isCMake" : true,
			"isExternal" : true,
			"path" : "/usr/share/cmake-3.22/Modules/CheckCXXCompilerFlag.cmake"
		},
		{
			"isCMake" : true,
			"isExternal" : true,
			"path" : "/usr/share/cmake-3.22/Modules/CheckCXXSourceCompiles.cmake"
		},
		{
			"isCMake" : true,
			"isExternal" : true,
			"path" : "/usr/share/cmake-3.22/Modules/Internal/CheckCompilerFlag.cmake"
		},
		{
			"isCMake" : true,
			"isExternal" : true,
			"path" : "/usr/share/cmake-3.22/Modules/GNUInstallDirs.cmake"
		},
		{
			"isCMake" : true,
			"isExternal" : true,
			"path" : "/usr/share/cmake-3.22/Modules/FindThreads.cmake"
		},
		{
			"isCMake" : true,
			"isExternal" : true,
			"path" : "/usr/share/cmake-3.22/Modules/CheckLibraryExists.cmake"
		},
		{
			"isCMake" : true,
			"isExternal" : true,
			"path" : "/usr/share/cmake-3.22/Modules/CheckIncludeFile.cmake"
		},
		{
			"isCMake" : true,
			"isExternal" : true,
			"path" : "/usr/share/cmake-3.22/Modules/CheckCSourceCompiles.cmake"
		},
		{
			"isCMake" : true,
			"isExternal" : true,
			"path" : "/usr/share/cmake-3.22/Modules/FindPackageHandleStandardArgs.cmake"
		},
		{
			"isCMake" : true,
			"isExternal" : true,
			"path" : "/usr/share/cmake-3.22/Modules/FindPackageMessage.cmake"
		},
		{
			"isCMake" : true,
			"isExternal" : true,
			"path" : "/usr/share/cmake-3.22/Modules/exportheader.cmake.in"
		},
		{
			"path" : "third-party/replxx/replxx-config.cmake.in"
		},
		{
			"isCMake" : true,
			"isExternal" : true,
			"path" : "/usr/share/cmake-3.22/Modules/BasicConfigVersion-AnyNewerVersion.cmake.in"
		},
		{
			"path" : "third-party/sqlite3/CMakeLists.txt"
		},
		{
			"isCMake" : true,
			"isExternal" : true,
			"path" : "/usr/share/cmake-3.22/Modules/FindThreads.cmake"
		},
		{
			"isCMake" : true,
			"isExternal" : true,
			"path" : "/usr/share/cmake-3.22/Modules/CheckLibraryExists.cmake"
		},
		{
			"isCMake" : true,
			"isExternal" : true,
			"path" : "/usr/share/cmake-3.22/Modules/CheckIncludeFile.cmake"
		},
		{
			"isCMake" : true,
			"isExternal" : true,
			"path" : "/usr/share/cmake-3.22/Modules/CheckCSourceCompiles.cmake"
		},
		{
			"isCMake" : true,
			"isExternal" : true,
			"path" : "/usr/share/cmake-3.22/Modules/FindPackageHandleStandardArgs.cmake"
		},
		{
			"isCMake" : true,
			"isExternal" : true,
			"path" : "/usr/share/cmake-3.22/Modules/FindPackageMessage.cmake"
		},
		{
			"path" : "third-party/tree-sitter/CMakeLists.txt"
		},
		{
			"path" : "third-party/libtinyfiledialogs/CMakeLists.txt"
		},
		{
			"path" : "third-party/fmt/CMakeLists.txt"
		},
		{
			"isCMake" : true,
			"isExternal" : true,
			"path" : "/usr/share/cmake-3.22/Modules/CMakeParseArguments.cmake"
		},
		{
			"isCMake" : true,
			"isExternal" : true,
			"path" : "/usr/share/cmake-3.22/Modules/GNUInstallDirs.cmake"
		},
		{
			"isCMake" : true,
			"isExternal" : true,
			"path" : "/usr/share/cmake-3.22/Modules/CheckCXXCompilerFlag.cmake"
		},
		{
			"path" : "third-party/fmt/support/cmake/JoinPaths.cmake"
		},
		{
			"isCMake" : true,
			"isExternal" : true,
			"path" : "/usr/share/cmake-3.22/Modules/CMakePackageConfigHelpers.cmake"
		},
		{
			"isCMake" : true,
			"isExternal" : true,
			"path" : "/usr/share/cmake-3.22/Modules/WriteBasicConfigVersionFile.cmake"
		},
		{
			"isCMake" : true,
			"isExternal" : true,
			"path" : "/usr/share/cmake-3.22/Modules/BasicConfigVersion-AnyNewerVersion.cmake.in"
		},
		{
			"path" : "third-party/fmt/support/cmake/fmt.pc.in"
		},
		{
			"path" : "third-party/fmt/support/cmake/fmt-config.cmake.in"
		},
		{
			"path" : "common/CMakeLists.txt"
		},
		{
			"isCMake" : true,
			"isExternal" : true,
			"path" : "/usr/share/cmake-3.22/Modules/FindGit.cmake"
		},
		{
			"isCMake" : true,
			"isExternal" : true,
			"path" : "/usr/share/cmake-3.22/Modules/FindPackageHandleStandardArgs.cmake"
		},
		{
			"isCMake" : true,
			"isExternal" : true,
			"path" : "/usr/share/cmake-3.22/Modules/FindPackageMessage.cmake"
		},
		{
			"path" : "decompiler/CMakeLists.txt"
		},
		{
			"path" : "third-party/cubeb/CMakeLists.txt"
		},
		{
			"path" : "third-party/cubeb/cubeb/CMakeLists.txt"
		},
		{
			"isCMake" : true,
			"isExternal" : true,
			"path" : "/usr/share/cmake-3.22/Modules/GenerateExportHeader.cmake"
		},
		{
			"isCMake" : true,
			"isExternal" : true,
			"path" : "/usr/share/cmake-3.22/Modules/CheckCCompilerFlag.cmake"
		},
		{
			"isCMake" : true,
			"isExternal" : true,
			"path" : "/usr/share/cmake-3.22/Modules/CheckCXXCompilerFlag.cmake"
		},
		{
			"isCMake" : true,
			"isExternal" : true,
			"path" : "/usr/share/cmake-3.22/Modules/exportheader.cmake.in"
		},
		{
			"isCMake" : true,
			"isExternal" : true,
			"path" : "/usr/share/cmake-3.22/Modules/GNUInstallDirs.cmake"
		},
		{
			"isCMake" : true,
			"isExternal" : true,
			"path" : "/usr/share/cmake-3.22/Modules/CMakePackageConfigHelpers.cmake"
		},
		{
			"isCMake" : true,
			"isExternal" : true,
			"path" : "/usr/share/cmake-3.22/Modules/WriteBasicConfigVersionFile.cmake"
		},
		{
			"isCMake" : true,
			"isExternal" : true,
			"path" : "/usr/share/cmake-3.22/Modules/BasicConfigVersion-SameMajorVersion.cmake.in"
		},
		{
			"path" : "third-party/cubeb/cubeb/Config.cmake.in"
		},
		{
			"isCMake" : true,
			"isExternal" : true,
			"path" : "/usr/share/cmake-3.22/Modules/CheckIncludeFiles.cmake"
		},
		{
			"isCMake" : true,
			"isExternal" : true,
			"path" : "/usr/share/cmake-3.22/Modules/FindThreads.cmake"
		},
		{
			"isCMake" : true,
			"isExternal" : true,
			"path" : "/usr/share/cmake-3.22/Modules/CheckLibraryExists.cmake"
		},
		{
			"isCMake" : true,
			"isExternal" : true,
			"path" : "/usr/share/cmake-3.22/Modules/CheckIncludeFile.cmake"
		},
		{
			"isCMake" : true,
			"isExternal" : true,
			"path" : "/usr/share/cmake-3.22/Modules/CheckCSourceCompiles.cmake"
		},
		{
			"isCMake" : true,
			"isExternal" : true,
			"path" : "/usr/share/cmake-3.22/Modules/FindPackageHandleStandardArgs.cmake"
		},
		{
			"isCMake" : true,
			"isExternal" : true,
			"path" : "/usr/share/cmake-3.22/Modules/FindPackageMessage.cmake"
		},
		{
			"path" : "third-party/cubeb/cubeb/cmake/compile_tests/oss_is_v4.c"
		},
		{
			"isCMake" : true,
			"isExternal" : true,
			"path" : "/usr/share/cmake-3.22/Modules/FindDoxygen.cmake"
		},
		{
			"isCMake" : true,
			"isExternal" : true,
			"path" : "/usr/share/cmake-3.22/Modules/FindPackageHandleStandardArgs.cmake"
		},
		{
			"isCMake" : true,
			"isExternal" : true,
			"path" : "/usr/share/cmake-3.22/Modules/FindPackageMessage.cmake"
		},
		{
			"path" : "lsp/CMakeLists.txt"
		},
		{
			"path" : "third-party/libco/CMakeLists.txt"
		},
		{
			"path" : "third-party/zstd/CMakeLists.txt"
		},
		{
			"path" : "third-party/SDL/CMakeLists.txt"
		},
		{
			"isCMake" : true,
			"isExternal" : true,
			"path" : "/usr/share/cmake-3.22/Modules/CheckLibraryExists.cmake"
		},
		{
			"isCMake" : true,
			"isExternal" : true,
			"path" : "/usr/share/cmake-3.22/Modules/CheckIncludeFiles.cmake"
		},
		{
			"isCMake" : true,
			"isExternal" : true,
			"path" : "/usr/share/cmake-3.22/Modules/CheckIncludeFile.cmake"
		},
		{
			"isCMake" : true,
			"isExternal" : true,
			"path" : "/usr/share/cmake-3.22/Modules/CheckLanguage.cmake"
		},
		{
			"isCMake" : true,
			"isExternal" : true,
			"path" : "/usr/share/cmake-3.22/Modules/CheckSymbolExists.cmake"
		},
		{
			"isCMake" : true,
			"isExternal" : true,
			"path" : "/usr/share/cmake-3.22/Modules/CheckCSourceCompiles.cmake"
		},
		{
			"isCMake" : true,
			"isExternal" : true,
			"path" : "/usr/share/cmake-3.22/Modules/CheckCSourceRuns.cmake"
		},
		{
			"isCMake" : true,
			"isExternal" : true,
			"path" : "/usr/share/cmake-3.22/Modules/CheckCCompilerFlag.cmake"
		},
		{
			"isCMake" : true,
			"isExternal" : true,
			"path" : "/usr/share/cmake-3.22/Modules/CheckCXXCompilerFlag.cmake"
		},
		{
			"isCMake" : true,
			"isExternal" : true,
			"path" : "/usr/share/cmake-3.22/Modules/CheckStructHasMember.cmake"
		},
		{
			"isCMake" : true,
			"isExternal" : true,
			"path" : "/usr/share/cmake-3.22/Modules/CMakeDependentOption.cmake"
		},
		{
			"isCMake" : true,
			"isExternal" : true,
			"path" : "/usr/share/cmake-3.22/Modules/CMakePushCheckState.cmake"
		},
		{
			"isCMake" : true,
			"isExternal" : true,
			"path" : "/usr/share/cmake-3.22/Modules/GNUInstallDirs.cmake"
		},
		{
			"isCMake" : true,
			"isExternal" : true,
			"path" : "/usr/share/cmake-3.22/Modules/FindPkgConfig.cmake"
		},
		{
			"isCMake" : true,
			"isExternal" : true,
			"path" : "/usr/share/cmake-3.22/Modules/FindPackageHandleStandardArgs.cmake"
		},
		{
			"isCMake" : true,
			"isExternal" : true,
			"path" : "/usr/share/cmake-3.22/Modules/FindPackageMessage.cmake"
		},
		{
			"path" : "third-party/SDL/cmake/macros.cmake"
		},
		{
			"path" : "third-party/SDL/cmake/sdlchecks.cmake"
		},
		{
			"isCMake" : true,
			"isExternal" : true,
			"path" : "/usr/share/cmake-3.22/Modules/CMakeParseArguments.cmake"
		},
		{
			"path" : "third-party/SDL/cmake/sdlfind.cmake"
		},
		{
			"path" : "third-party/SDL/cmake/sdlplatform.cmake"
		},
		{
			"path" : "third-party/SDL/cmake/CheckCPUArchitecture.cmake"
		},
		{
			"isCMake" : true,
			"isExternal" : true,
			"path" : "/usr/share/cmake-3.22/Modules/CheckCSourceCompiles.cmake"
		},
		{
			"isCMake" : true,
			"isExternal" : true,
			"path" : "/usr/share/cmake-3.22/Modules/CMakePushCheckState.cmake"
		},
		{
			"path" : "third-party/SDL/include/SDL_config.h.cmake"
		},
		{
			"isCMake" : true,
			"isExternal" : true,
			"path" : "/usr/share/cmake-3.22/Modules/FindGit.cmake"
		},
		{
			"isCMake" : true,
			"isExternal" : true,
			"path" : "/usr/share/cmake-3.22/Modules/FindPackageHandleStandardArgs.cmake"
		},
		{
			"isCMake" : true,
			"isExternal" : true,
			"path" : "/usr/share/cmake-3.22/Modules/FindPackageMessage.cmake"
		},
		{
			"path" : "third-party/SDL/include/SDL_revision.h.cmake"
		},
		{
			"path" : "third-party/SDL/sdl2.pc.in"
		},
		{
			"path" : "third-party/SDL/sdl2-config.in"
		},
		{
			"path" : "third-party/SDL/SDL2.spec.in"
		},
		{
			"path" : "third-party/SDL/cmake_uninstall.cmake.in"
		},
		{
			"isGenerated" : true,
			"path" : "build/Release/bin/third-party/SDL/SDL_config.h.intermediate"
		},
		{
			"path" : "third-party/imgui/CMakeLists.txt"
		},
		{
			"path" : "game/CMakeLists.txt"
		},
		{
			"isGenerated" : true,
			"path" : "build/Release/bin/CMakeFiles/3.22.1/CMakeASM_NASMCompiler.cmake"
		},
		{
			"isCMake" : true,
			"isExternal" : true,
			"path" : "/usr/share/cmake-3.22/Modules/CMakeASM_NASMInformation.cmake"
		},
		{
			"isCMake" : true,
			"isExternal" : true,
			"path" : "/usr/share/cmake-3.22/Modules/CMakeASMInformation.cmake"
		},
		{
			"path" : "game/sound/CMakeLists.txt"
		},
		{
			"path" : "goalc/CMakeLists.txt"
		},
		{
			"path" : "tools/CMakeLists.txt"
		},
		{
			"path" : "tools/level_tools/CMakeLists.txt"
		},
		{
			"path" : "third-party/googletest/CMakeLists.txt"
		},
		{
			"isCMake" : true,
			"isExternal" : true,
			"path" : "/usr/share/cmake-3.22/Modules/CMakeDependentOption.cmake"
		},
		{
			"isCMake" : true,
			"isExternal" : true,
			"path" : "/usr/share/cmake-3.22/Modules/GNUInstallDirs.cmake"
		},
		{
			"path" : "third-party/googletest/googlemock/CMakeLists.txt"
		},
		{
			"isCMake" : true,
			"isExternal" : true,
			"path" : "/usr/share/cmake-3.22/Modules/FindThreads.cmake"
		},
		{
			"isCMake" : true,
			"isExternal" : true,
			"path" : "/usr/share/cmake-3.22/Modules/CheckLibraryExists.cmake"
		},
		{
			"isCMake" : true,
			"isExternal" : true,
			"path" : "/usr/share/cmake-3.22/Modules/CheckIncludeFile.cmake"
		},
		{
			"isCMake" : true,
			"isExternal" : true,
			"path" : "/usr/share/cmake-3.22/Modules/CheckCSourceCompiles.cmake"
		},
		{
			"isCMake" : true,
			"isExternal" : true,
			"path" : "/usr/share/cmake-3.22/Modules/FindPackageHandleStandardArgs.cmake"
		},
		{
			"isCMake" : true,
			"isExternal" : true,
			"path" : "/usr/share/cmake-3.22/Modules/FindPackageMessage.cmake"
		},
		{
			"path" : "third-party/googletest/googlemock/cmake/gmock.pc.in"
		},
		{
			"path" : "third-party/googletest/googlemock/cmake/gmock_main.pc.in"
		},
		{
			"path" : "third-party/googletest/googletest/CMakeLists.txt"
		},
		{
			"path" : "third-party/googletest/googletest/cmake/internal_utils.cmake"
		},
		{
			"isCMake" : true,
			"isExternal" : true,
			"path" : "/usr/share/cmake-3.22/Modules/FindPython.cmake"
		},
		{
			"isCMake" : true,
			"isExternal" : true,
			"path" : "/usr/share/cmake-3.22/Modules/FindPython/Support.cmake"
		},
		{
			"isCMake" : true,
			"isExternal" : true,
			"path" : "/usr/share/cmake-3.22/Modules/FindPackageHandleStandardArgs.cmake"
		},
		{
			"isCMake" : true,
			"isExternal" : true,
			"path" : "/usr/share/cmake-3.22/Modules/FindPackageMessage.cmake"
		},
		{
			"isCMake" : true,
			"isExternal" : true,
			"path" : "/usr/share/cmake-3.22/Modules/FindThreads.cmake"
		},
		{
			"isCMake" : true,
			"isExternal" : true,
			"path" : "/usr/share/cmake-3.22/Modules/CheckLibraryExists.cmake"
		},
		{
			"isCMake" : true,
			"isExternal" : true,
			"path" : "/usr/share/cmake-3.22/Modules/CheckIncludeFile.cmake"
		},
		{
			"isCMake" : true,
			"isExternal" : true,
			"path" : "/usr/share/cmake-3.22/Modules/CheckCSourceCompiles.cmake"
		},
		{
			"isCMake" : true,
			"isExternal" : true,
			"path" : "/usr/share/cmake-3.22/Modules/FindPackageHandleStandardArgs.cmake"
		},
		{
			"isCMake" : true,
			"isExternal" : true,
			"path" : "/usr/share/cmake-3.22/Modules/FindPackageMessage.cmake"
		},
		{
			"isCMake" : true,
			"isExternal" : true,
			"path" : "/usr/share/cmake-3.22/Modules/CMakePackageConfigHelpers.cmake"
		},
		{
			"isCMake" : true,
			"isExternal" : true,
			"path" : "/usr/share/cmake-3.22/Modules/WriteBasicConfigVersionFile.cmake"
		},
		{
			"isCMake" : true,
			"isExternal" : true,
			"path" : "/usr/share/cmake-3.22/Modules/BasicConfigVersion-AnyNewerVersion.cmake.in"
		},
		{
			"path" : "third-party/googletest/googletest/cmake/Config.cmake.in"
		},
		{
			"path" : "third-party/googletest/googletest/cmake/gtest.pc.in"
		},
		{
			"path" : "third-party/googletest/googletest/cmake/gtest_main.pc.in"
		},
		{
			"path" : "third-party/lzokay/CMakeLists.txt"
		},
		{
			"isCMake" : true,
			"isExternal" : true,
			"path" : "/usr/share/cmake-3.22/Modules/CMakePackageConfigHelpers.cmake"
		},
		{
			"isCMake" : true,
			"isExternal" : true,
			"path" : "/usr/share/cmake-3.22/Modules/WriteBasicConfigVersionFile.cmake"
		},
		{
			"isCMake" : true,
			"isExternal" : true,
			"path" : "/usr/share/cmake-3.22/Modules/BasicConfigVersion-SameMajorVersion.cmake.in"
		},
		{
			"path" : "third-party/lzokay/Config.cmake.in"
		},
		{
			"path" : "third-party/lzokay/lzokay-c/CMakeLists.txt"
		},
		{
			"path" : "third-party/stb_image/CMakeLists.txt"
		},
		{
			"path" : "third-party/tiny_gltf/CMakeLists.txt"
		},
		{
			"path" : "third-party/xdelta3/CMakeLists.txt"
		},
		{
			"path" : "third-party/discord-rpc/CMakeLists.txt"
		},
		{
			"isCMake" : true,
			"isExternal" : true,
			"path" : "/usr/share/cmake-3.22/Modules/GNUInstallDirs.cmake"
		},
		{
			"path" : "third-party/discord-rpc/src/CMakeLists.txt"
		},
		{
			"path" : "third-party/zydis/CMakeLists.txt"
		},
		{
			"isCMake" : true,
			"isExternal" : true,
			"path" : "/usr/share/cmake-3.22/Modules/GNUInstallDirs.cmake"
		},
		{
			"isCMake" : true,
			"isExternal" : true,
			"path" : "/usr/share/cmake-3.22/Modules/CMakePackageConfigHelpers.cmake"
		},
		{
			"isCMake" : true,
			"isExternal" : true,
			"path" : "/usr/share/cmake-3.22/Modules/WriteBasicConfigVersionFile.cmake"
		},
		{
			"path" : "third-party/zydis/cmake/zydis-config.cmake.in"
		},
		{
			"isCMake" : true,
			"isExternal" : true,
			"path" : "/usr/share/cmake-3.22/Modules/BasicConfigVersion-SameMajorVersion.cmake.in"
		},
		{
			"path" : "third-party/zydis/dependencies/zycore/CMakeLists.txt"
		},
		{
			"isCMake" : true,
			"isExternal" : true,
			"path" : "/usr/share/cmake-3.22/Modules/GNUInstallDirs.cmake"
		},
		{
			"isCMake" : true,
			"isExternal" : true,
			"path" : "/usr/share/cmake-3.22/Modules/CMakePackageConfigHelpers.cmake"
		},
		{
			"isCMake" : true,
			"isExternal" : true,
			"path" : "/usr/share/cmake-3.22/Modules/WriteBasicConfigVersionFile.cmake"
		},
		{
			"path" : "third-party/zydis/dependencies/zycore/cmake/zyan-functions.cmake"
		},
		{
			"isCMake" : true,
			"isExternal" : true,
			"path" : "/usr/share/cmake-3.22/Modules/FindThreads.cmake"
		},
		{
			"isCMake" : true,
			"isExternal" : true,
			"path" : "/usr/share/cmake-3.22/Modules/CheckLibraryExists.cmake"
		},
		{
			"isCMake" : true,
			"isExternal" : true,
			"path" : "/usr/share/cmake-3.22/Modules/CheckIncludeFile.cmake"
		},
		{
			"isCMake" : true,
			"isExternal" : true,
			"path" : "/usr/share/cmake-3.22/Modules/CheckCSourceCompiles.cmake"
		},
		{
			"isCMake" : true,
			"isExternal" : true,
			"path" : "/usr/share/cmake-3.22/Modules/FindPackageHandleStandardArgs.cmake"
		},
		{
			"isCMake" : true,
			"isExternal" : true,
			"path" : "/usr/share/cmake-3.22/Modules/FindPackageMessage.cmake"
		},
		{
			"path" : "third-party/zydis/dependencies/zycore/cmake/zycore-config.cmake.in"
		},
		{
			"isCMake" : true,
			"isExternal" : true,
			"path" : "/usr/share/cmake-3.22/Modules/BasicConfigVersion-SameMajorVersion.cmake.in"
		},
		{
			"isCMake" : true,
			"isExternal" : true,
			"path" : "/usr/share/cmake-3.22/Modules/FindDoxygen.cmake"
		},
		{
			"isCMake" : true,
			"isExternal" : true,
			"path" : "/usr/share/cmake-3.22/Modules/FindPackageHandleStandardArgs.cmake"
		},
		{
			"isCMake" : true,
			"isExternal" : true,
			"path" : "/usr/share/cmake-3.22/Modules/FindPackageMessage.cmake"
		}
	],
	"kind" : "cmakeFiles",
	"paths" : 
	{
		"build" : "/home/zachary/.vs/jak-project/build/Release/bin",
		"source" : "/home/zachary/.vs/jak-project"
	},
	"version" : 
	{
		"major" : 1,
		"minor" : 0
	}
}
